ldt_identity_client_staging/__init__.py
ldt_identity_client_staging/api_client.py
ldt_identity_client_staging/api_response.py
ldt_identity_client_staging/configuration.py
ldt_identity_client_staging/exceptions.py
ldt_identity_client_staging/py.typed
ldt_identity_client_staging/rest.py
ldt_identity_client_staging/api/__init__.py
ldt_identity_client_staging/api/invitations_api.py
ldt_identity_client_staging/api/organizations_api.py
ldt_identity_client_staging/api/service_accounts_api.py
ldt_identity_client_staging/api/session_api.py
ldt_identity_client_staging/api/user_roles_api.py
ldt_identity_client_staging/api/users_api.py
ldt_identity_client_staging/models/__init__.py
ldt_identity_client_staging/models/add_org_user_request_inner.py
ldt_identity_client_staging/models/create_service_account200_response.py
ldt_identity_client_staging/models/create_service_account200_response_role.py
ldt_identity_client_staging/models/create_service_account_request.py
ldt_identity_client_staging/models/delete_org_users_request.py
ldt_identity_client_staging/models/delete_service_account200_response.py
ldt_identity_client_staging/models/get_service_accounts200_response_inner.py
ldt_identity_client_staging/models/get_service_accounts200_response_inner_role.py
ldt_identity_client_staging/models/initiate_password_reset_request.py
ldt_identity_client_staging/models/invitation.py
ldt_identity_client_staging/models/invitation_body.py
ldt_identity_client_staging/models/org.py
ldt_identity_client_staging/models/org_body.py
ldt_identity_client_staging/models/post_session_google200_response.py
ldt_identity_client_staging/models/post_session_google200_response_orgs_inner.py
ldt_identity_client_staging/models/post_session_google200_response_services_inner.py
ldt_identity_client_staging/models/post_session_google_request.py
ldt_identity_client_staging/models/post_session_request.py
ldt_identity_client_staging/models/regenerate_client_secret200_response.py
ldt_identity_client_staging-1.0.0.dist-info/METADATA
ldt_identity_client_staging-1.0.0.dist-info/WHEEL
ldt_identity_client_staging-1.0.0.dist-info/top_level.txt
ldt_identity_client_staging-1.0.0.dist-info/RECORD
